annadb/__init__.py
annadb/collection.py
annadb/connection.py
annadb/console.py
annadb/constants.py
annadb/data_types/__init__.py
annadb/data_types/constants.py
annadb/data_types/journal.py
annadb/data_types/map.py
annadb/data_types/modifier.py
annadb/data_types/pair.py
annadb/data_types/primitive.py
annadb/data_types/types_map.py
annadb/data_types/tyson.py
annadb/data_types/vector.py
annadb/dump.py
annadb/exceptions.py
annadb/query/__init__.py
annadb/query/base.py
annadb/query/delete/__init__.py
annadb/query/delete/query.py
annadb/query/find/__init__.py
annadb/query/find/operators.py
annadb/query/find/query.py
annadb/query/get/__init__.py
annadb/query/get/query.py
annadb/query/insert/__init__.py
annadb/query/insert/query.py
annadb/query/limit/__init__.py
annadb/query/limit/query.py
annadb/query/offset/__init__.py
annadb/query/offset/query.py
annadb/query/path.py
annadb/query/project/__init__.py
annadb/query/project/operators.py
annadb/query/project/query.py
annadb/query/query_set.py
annadb/query/sort/__init__.py
annadb/query/sort/operators.py
annadb/query/sort/query.py
annadb/query/types.py
annadb/query/update/__init__.py
annadb/query/update/operators.py
annadb/query/update/query.py
annadb/response.py
annadb/shell/__init__.py
annadb/transaction.py
annadb-0.1.4.dist-info/entry_points.txt
annadb-0.1.4.dist-info/LICENSE
annadb-0.1.4.dist-info/WHEEL
annadb-0.1.4.dist-info/METADATA
annadb-0.1.4.dist-info/RECORD
